README.rst
setup.py
What.egg-info/PKG-INFO
What.egg-info/SOURCES.txt
What.egg-info/dependency_links.txt
What.egg-info/top_level.txt
What.egg-info/zip-safe
what/__init__.py
what/exceptions.py
what/ringbuffer.py
what/six.py