Metadata-Version: 1.1
Name: What
Version: 0.5.0
Summary: A helper for testing process output
Home-page: http://github.com/cenkalti/what
Author: Cenk Alti
Author-email: cenkalti@gmail.com
License: UNKNOWN
Keywords: unittest process subprocess
Platform: UNKNOWN
Classifier: Development Status :: 4 - Beta
Classifier: Intended Audience :: Developers
Classifier: License :: OSI Approved :: Apache Software License
Classifier: Operating System :: OS Independent
Classifier: Programming Language :: Python
Classifier: Topic :: Software Development :: Testing
